singleton_meta/__init__.py
singleton_meta/main.py
singleton_meta-0.1.3.dist-info/LICENSE
singleton_meta-0.1.3.dist-info/METADATA
singleton_meta-0.1.3.dist-info/WHEEL
singleton_meta-0.1.3.dist-info/top_level.txt
singleton_meta-0.1.3.dist-info/RECORD
