Metadata-Version: 2.1
Name: singleton_meta
Version: 0.1.3
Summary: create perfect singletons
Home-page: https://github.com/centroid457/
Author: Andrei Starichenko
Author-email: centroid@mail.ru
Project-URL: Source, https://github.com/centroid457/singleton_meta
Keywords: singleton,singleton meta,singleton call,singleton new
Classifier: Topic :: Software Development :: Libraries :: Python Modules
Classifier: License :: OSI Approved :: MIT License
Classifier: Programming Language :: Python
Classifier: Programming Language :: Python :: 3 :: Only
Classifier: Programming Language :: Python :: 3.11
Classifier: Operating System :: OS Independent
Classifier: Intended Audience :: Developers
Classifier: Natural Language :: English
Classifier: Typing :: Typed
Requires-Python: >=3.6
License-File: LICENSE
